pyhrms/__init__.py
pyhrms/pyhrms.py
pyhrms-1.0.9.dist-info/METADATA
pyhrms-1.0.9.dist-info/WHEEL
pyhrms-1.0.9.dist-info/top_level.txt
pyhrms-1.0.9.dist-info/RECORD
