Metadata-Version: 2.1
Name: pyhrms
Version: 1.0.9
Summary: A powerful GC/LC-HRMS data analysis tool
Home-page: https://github.com/WangRui5/PyHRMS.git
Author: Wang Rui
Author-email: wtrt7009@gmail.com
Classifier: Programming Language :: Python :: 3
Classifier: License :: OSI Approved :: MIT License
Classifier: Operating System :: OS Independent
Requires-Python: >=3.6
Requires-Dist: numpy>=1.19.2
Requires-Dist: pandas>=1.3.3
Requires-Dist: matplotlib>=3.3.2
Requires-Dist: pymzml>=2.4.7
Requires-Dist: scipy>=1.6.2
Requires-Dist: molmass==2021.6.18
Requires-Dist: tqdm>=4.62.3
Requires-Dist: openpyxl>=3.1.4
Requires-Dist: networkx>=2.6.3
Requires-Dist: scikit-learn>=1.0.2
Requires-Dist: requests
Requires-Dist: beautifulsoup4
Requires-Dist: fake-useragent>=2.0.3
